odoo/addons/edi_ediversa_oca/README.rst
odoo/addons/edi_ediversa_oca/__init__.py
odoo/addons/edi_ediversa_oca/__manifest__.py
odoo/addons/edi_ediversa_oca/components/__init__.py
odoo/addons/edi_ediversa_oca/components/ediversa_api.py
odoo/addons/edi_ediversa_oca/data/edi.xml
odoo/addons/edi_ediversa_oca/data/ir_config_parameter.xml
odoo/addons/edi_ediversa_oca/i18n/edi_ediversa_oca.pot
odoo/addons/edi_ediversa_oca/i18n/it.po
odoo/addons/edi_ediversa_oca/models/__init__.py
odoo/addons/edi_ediversa_oca/models/res_company.py
odoo/addons/edi_ediversa_oca/models/res_partner.py
odoo/addons/edi_ediversa_oca/readme/CONFIGURE.md
odoo/addons/edi_ediversa_oca/readme/CONTRIBUTORS.md
odoo/addons/edi_ediversa_oca/readme/DESCRIPTION.md
odoo/addons/edi_ediversa_oca/static/description/icon.png
odoo/addons/edi_ediversa_oca/static/description/index.html
odoo/addons/edi_ediversa_oca/views/res_company_views.xml
odoo/addons/edi_ediversa_oca/views/res_partner_views.xml
odoo_addon_edi_ediversa_oca-17.0.1.0.0.6.dist-info/METADATA
odoo_addon_edi_ediversa_oca-17.0.1.0.0.6.dist-info/WHEEL
odoo_addon_edi_ediversa_oca-17.0.1.0.0.6.dist-info/top_level.txt
odoo_addon_edi_ediversa_oca-17.0.1.0.0.6.dist-info/RECORD
